sdkite/__init__.py
sdkite/_version.py
sdkite/adapter.py
sdkite/client.py
sdkite/exceptions.py
sdkite/pagination.py
sdkite/py.typed
sdkite/utils.py
sdkite/http/__init__.py
sdkite/http/_stringescape.py
sdkite/http/adapter.py
sdkite/http/auth.py
sdkite/http/engine_replay.py
sdkite/http/engine_requests.py
sdkite/http/exceptions.py
sdkite/http/model.py
sdkite/http/utils.py
sdkite-0.5.0.dist-info/LICENSE.txt
sdkite-0.5.0.dist-info/METADATA
sdkite-0.5.0.dist-info/WHEEL
sdkite-0.5.0.dist-info/top_level.txt
sdkite-0.5.0.dist-info/RECORD
