Metadata-Version: 2.1
Name: sdkite
Version: 0.5.0
Summary: Simple framework for building SDKs and API clients
Home-page: https://github.com/rogdham/sdkite
Author: Rogdham
Author-email: contact@rogdham.net
License: MIT
Project-URL: Documentation, https://sdkite.rogdham.net/
Project-URL: Source, https://github.com/rogdham/sdkite
Keywords: sdk api client toolkit framework
Platform: any
Classifier: Development Status :: 2 - Pre-Alpha
Classifier: License :: OSI Approved :: MIT License
Classifier: Operating System :: OS Independent
Classifier: Programming Language :: Python
Classifier: Programming Language :: Python :: 3
Classifier: Programming Language :: Python :: 3 :: Only
Classifier: Programming Language :: Python :: 3.7
Classifier: Programming Language :: Python :: 3.8
Classifier: Programming Language :: Python :: 3.9
Classifier: Programming Language :: Python :: 3.10
Classifier: Programming Language :: Python :: 3.11
Classifier: Topic :: Communications
Classifier: Topic :: Utilities
Classifier: Topic :: Internet
Classifier: Topic :: Internet :: WWW/HTTP
Classifier: Topic :: Software Development
Classifier: Topic :: Software Development :: Libraries
Classifier: Topic :: Software Development :: Libraries :: Application Frameworks
Requires-Python: >=3.7
License-File: LICENSE.txt
Requires-Dist: requests (>=2.28.1)
Requires-Dist: tenacity (>=8.2.2)
Requires-Dist: typing-extensions (>=4.5.0) ; python_version < "3.11"
Requires-Dist: backports.cached-property (>=1.0.2) ; python_version < "3.8"
